gobattlesim/Engine.py
gobattlesim/GameMaster.py
gobattlesim/Matrix.py
gobattlesim/Move.py
gobattlesim/PokeQuery.py
gobattlesim/Pokemon.py
gobattlesim/__init__.py
gobattlesim/__main__.py
gobattlesim/libGoBattleSim.dll
gobattlesim-0.8.1.dist-info/LICENSE
gobattlesim-0.8.1.dist-info/METADATA
gobattlesim-0.8.1.dist-info/WHEEL
gobattlesim-0.8.1.dist-info/top_level.txt
gobattlesim-0.8.1.dist-info/RECORD
