Metadata-Version: 2.1
Name: gobattlesim
Version: 0.8.1
Summary: UNKNOWN
Home-page: https://github.com/ymenghank/GoBattleSim-Python
License: UNKNOWN
Platform: UNKNOWN
Classifier: Programming Language :: Python :: 3
Classifier: License :: OSI Approved :: GNU General Public License v3 (GPLv3)
Classifier: Development Status :: 4 - Beta
